workout_builder_streamlit/__init__.py
workout_builder_streamlit/frontend/.gitignore
workout_builder_streamlit/frontend/eslint.config.js
workout_builder_streamlit/frontend/index.html
workout_builder_streamlit/frontend/package-lock.json
workout_builder_streamlit/frontend/package.json
workout_builder_streamlit/frontend/postcss.config.js
workout_builder_streamlit/frontend/tailwind.config.js
workout_builder_streamlit/frontend/tsconfig.app.json
workout_builder_streamlit/frontend/tsconfig.json
workout_builder_streamlit/frontend/tsconfig.node.json
workout_builder_streamlit/frontend/vite.config.ts
workout_builder_streamlit/frontend/dist/index.html
workout_builder_streamlit/frontend/dist/assets/index-B-3eHEOw.css
workout_builder_streamlit/frontend/dist/assets/index-CWhqZrCq.js
workout_builder_streamlit/frontend/project/.gitignore
workout_builder_streamlit/frontend/project/.bolt/config.json
workout_builder_streamlit/frontend/project/.bolt/prompt
workout_builder_streamlit/frontend/src/App.tsx
workout_builder_streamlit/frontend/src/index.css
workout_builder_streamlit/frontend/src/main.tsx
workout_builder_streamlit/frontend/src/vite-env.d.ts
workout_builder_streamlit/frontend/src/components/WorkoutBlock.tsx
workout_builder_streamlit/frontend/src/types/workout.ts
workout_builder_streamlit-0.1.1.dist-info/METADATA
workout_builder_streamlit-0.1.1.dist-info/WHEEL
workout_builder_streamlit-0.1.1.dist-info/entry_points.txt
workout_builder_streamlit-0.1.1.dist-info/RECORD
